opsramp/__init__.py
opsramp/api.py
opsramp/base.py
opsramp/binding.py
opsramp/cli.py
opsramp/devmgmt.py
opsramp/escalations.py
opsramp/examples.py
opsramp/first_response.py
opsramp/globalconfig.py
opsramp/integrations.py
opsramp/kb.py
opsramp/metrics.py
opsramp/mgmt_profiles.py
opsramp/monitoring.py
opsramp/msp.py
opsramp/rba.py
opsramp/resource_groups.py
opsramp/resources.py
opsramp/roles.py
opsramp/service_maps.py
opsramp/sites.py
opsramp/tenant.py
python_opsramp-3.5.0.dist-info/licenses/LICENSE
python_opsramp-3.5.0.dist-info/METADATA
python_opsramp-3.5.0.dist-info/WHEEL
python_opsramp-3.5.0.dist-info/entry_points.txt
python_opsramp-3.5.0.dist-info/top_level.txt
python_opsramp-3.5.0.dist-info/RECORD
