Metadata-Version: 2.4
Name: python-opsramp
Version: 3.5.0
Summary: Python language binding for the Opsramp API
Home-page: https://github.com/HewlettPackard/python-opsramp
Author: HPE GreenLake SRE
Author-email: eemz@hpe.com
License: Apache 2.0
Keywords: opsramp
Classifier: Development Status :: 5 - Production/Stable
Classifier: Intended Audience :: Developers
Classifier: Programming Language :: Python :: 3
Classifier: License :: OSI Approved :: Apache Software License
Classifier: Topic :: Software Development :: Libraries
Classifier: Operating System :: OS Independent
Requires-Python: >=3.6
License-File: LICENSE
Requires-Dist: requests
Requires-Dist: simplejson
Requires-Dist: urllib3
Dynamic: description
Dynamic: description-content-type
Dynamic: license-file
Dynamic: requires-dist
